[
  {
    "id": 1,
    "name": "Sweater Bowie",
    "price": 4500,
    "img": "/images/IMG_0503.jpg",
    "description": "Lorem ipsum dolor sit amet consectetur, adipisicing elit. Fuga suscipit soluta voluptas error fugit minima a dolorem? Repellat officiis corporis nesciunt temporibus!",
    "gender": "niñas",
    "discount": 0.05
  },
  {
    "id": 2,
    "name": "Sweater Freddie",
    "price": 4500,
    "img": "/images/IMG_0501.jpg",
    "description": "Lorem ipsum dolor sit amet consectetur, adipisicing elit. Fuga suscipit soluta voluptas error fugit minima a dolorem? Repellat officiis corporis nesciunt temporibus!",
    "gender": "niños",
    "discount": 0
  },
  {
    "id": 3,
    "name": "Gorrito cebra",
    "price": 2200,
    "img": "/images/IMG_gorrito_Cebra.jpg",
    "description": "Lorem ipsum dolor sit amet consectetur, adipisicing elit. Fuga suscipit soluta voluptas error fugit minima a dolorem? Repellat officiis corporis nesciunt temporibus!",
    "gender": "niños",
    "discount": 0
  },
  {
    "id": 4,
    "name": "Gorrito frutilla",
    "price": 2200,
    "img": "/images/IMG_gorrito_Frutilla.jpg",
    "description": "Lorem ipsum dolor sit amet consectetur, adipisicing elit. Fuga suscipit soluta voluptas error fugit minima a dolorem? Repellat officiis corporis nesciunt temporibus!",
    "gender": "niñas",
    "discount": 0
  },
  {
    "id": 5,
    "name": "Chaleco bosque",
    "price": 4500,
    "img": "/images/IMG_0498.jpg",
    "description": "Lorem ipsum dolor sit amet consectetur, adipisicing elit. Fuga suscipit soluta voluptas error fugit minima a dolorem? Repellat officiis corporis nesciunt temporibus!",
    "gender": "niños",
    "discount": 0.2
  },
  {
    "id": 6,
    "name": "Gorrito tricolor",
    "price": 2200,
    "img": "/images/IMG_0502.jpg",
    "description": "Lorem ipsum dolor sit amet consectetur, adipisicing elit. Fuga suscipit soluta voluptas error fugit minima a dolorem? Repellat officiis corporis nesciunt temporibus!",
    "gender": "niños",
    "discount": 0
  },
  {
    "id": 7,
    "name": "Sweater Jirafa",
    "description": "lorem ipsum",
    "price": "4500",
    "img": "/images/IMG_0495.jpg",
    "gender": "niñas",
    "discount": 0.1
  },
  {
    "id": 8,
    "name": "Gorrito militar",
    "description": "lorem ipsum",
    "price": "2200",
    "img": "/images/IMG_0505.jpg",
    "gender": "niños",
    "discount": 0.4
  },
  {
    "id": 9,
    "name": "polainas suerte",
    "description": "cruzando los dedos una vez más",
    "price": "2888",
    "img": "/images/polainas-tejidas-para-niñas-de-colores.jpg",
    "gender": "niñas",
    "discount": 0
  },
  {
    "id": 10,
    "name": "Combo miñons",
    "description": "Gorrito, guantes y bufandas de miñons.",
    "price": "4500",
    "img": "/images/product-img1652653924113.jpg",
    "gender": "niñas",
    "discount": 0.6
  }
]